{"2hB9Tu3H+VCiUK1qRVnelg==":"logo.png","e/WBEELULKqi/2dUoF8gdQ==":"gmf-muhendislik.jpg","YtRbetlqWAGiAjh3722RGw==":"gmf-muhendislik-edirne-gunes-enerjisi.jpg","2YyP/X+eC5r7oIuZhFqmpw==":"gmf-muhendislik-edirne-elektrik-tesisat-proje.jpg","GqWYKVnigl8AfY3xFhyHEQ==":"gmf-muhendislik-proje-cizim-yuksek-gerilim.jpg","sle12/ISS699Nfbqd8K1Lg==":"guven-elektrik.jpg","IS9Yo3hSodWIRjsCdEYyJA==":"inci-yurdu.jpg","nD7MBFZxrcH38Xvu8uRrkQ==":"kalyon.jpg","ty3OCIjXCqK0ZtSPDoZzEQ==":"limak.jpg","Do6YFVU2Isih4Z4MKoFVGw==":"tanap.jpg","ImIeCypLxJUmaLnfv/v0Qg==":"tekfen-holding.jpg","8xa4wGx7CQqrhuMTbUKLeg==":"trakya-cam-sanayi.jpg","nGnkc4QiHchkhv40G5ZCFg==":"tuvturk.jpg","h7luDMudrcIK6dcuouwquw==":"unal-peynircilik.png","XChKbADNNJMASmfW39XoBw==":"zorlu-enerji.jpg","mbvJV+QrJFBcm1QZbLBn+Q==":"icon.png"}